ghga_metadata_utils/__init__.py
ghga_metadata_utils/generators/__init__.py
ghga_metadata_utils/generators/jsonschemagen.py
ghga_metadata_utils/generators/pydanticgen.py
ghga_metadata_utils/validation_plugins/__init__.py
ghga_metadata_utils/validation_plugins/jsonschema_validation.py
tests/fixtures/__init__.py
tests/fixtures/utils.py
tests/integration/__init__.py
tests/integration/test_jsonschema_validation.py
tests/integration/fixtures/__init__.py
tests/integration/fixtures/utils.py
tests/unit/__init__.py
tests/unit/fixtures/__init__.py
tests/unit/fixtures/utils.py
ghga_metadata_utils-0.0.5.dist-info/LICENSE
ghga_metadata_utils-0.0.5.dist-info/METADATA
ghga_metadata_utils-0.0.5.dist-info/WHEEL
ghga_metadata_utils-0.0.5.dist-info/top_level.txt
ghga_metadata_utils-0.0.5.dist-info/RECORD
