Metadata-Version: 2.1
Name: ghga-metadata-utils
Version: 0.0.5
Summary: Utilities concerning the GHGA Metadata Schema
Home-page: https://github.com/ghga-de/ghga-metadata-utils
Author: German Human Genome Phenome Archive (GHGA)
Author-email: contact@ghga.de
License: Apache 2.0
Classifier: Operating System :: POSIX :: Linux
Classifier: Programming Language :: Python :: 3.9
Classifier: License :: OSI Approved :: Apache Software License
Classifier: Topic :: Internet :: WWW/HTTP :: HTTP Servers
Classifier: Topic :: Scientific/Engineering :: Bio-Informatics
Requires-Python: >=3.9
License-File: LICENSE
Requires-Dist: linkml (==1.2.15)
Requires-Dist: linkml-runtime (==1.2.16)
Requires-Dist: linkml-validator (>=0.4.2)
Provides-Extra: all
Requires-Dist: pytest (==7.1.1) ; extra == 'all'
Requires-Dist: pytest-cov (==3.0.0) ; extra == 'all'
Requires-Dist: mypy (==0.942) ; extra == 'all'
Requires-Dist: mypy-extensions (==0.4.3) ; extra == 'all'
Requires-Dist: pylint (==2.13.3) ; extra == 'all'
Requires-Dist: click (==8.1.2) ; extra == 'all'
Requires-Dist: black (==22.3.0) ; extra == 'all'
Requires-Dist: flake8 (==4.0.1) ; extra == 'all'
Requires-Dist: isort (==5.10.1) ; extra == 'all'
Requires-Dist: bandit (==1.7.4) ; extra == 'all'
Requires-Dist: pre-commit (==2.17.0) ; extra == 'all'
Requires-Dist: requests (==2.27.1) ; extra == 'all'
Requires-Dist: mkdocs (==1.3.0) ; extra == 'all'
Provides-Extra: dev
Requires-Dist: pytest (==7.1.1) ; extra == 'dev'
Requires-Dist: pytest-cov (==3.0.0) ; extra == 'dev'
Requires-Dist: mypy (==0.942) ; extra == 'dev'
Requires-Dist: mypy-extensions (==0.4.3) ; extra == 'dev'
Requires-Dist: pylint (==2.13.3) ; extra == 'dev'
Requires-Dist: click (==8.1.2) ; extra == 'dev'
Requires-Dist: black (==22.3.0) ; extra == 'dev'
Requires-Dist: flake8 (==4.0.1) ; extra == 'dev'
Requires-Dist: isort (==5.10.1) ; extra == 'dev'
Requires-Dist: bandit (==1.7.4) ; extra == 'dev'
Requires-Dist: pre-commit (==2.17.0) ; extra == 'dev'
Requires-Dist: requests (==2.27.1) ; extra == 'dev'
Requires-Dist: mkdocs (==1.3.0) ; extra == 'dev'
